{
    "error": "",
    "downloadTitle": "Power BI CSP Case Study - Vizion Solutions",
    "downloadDescription": "Power BI partner helps manufacturer reduce inefficiencies through collaborative mentality. ",
    "downloadFile": [
        {
            "isPrimary": "False",
            "name": "PowerBI CSP CaseStudy_Vizion Solutions.pdf",
            "url": "https://download.microsoft.com/download/7/9/d/79d6def0-72c1-406f-a38f-6545f64df41f/PowerBI CSP CaseStudy_Vizion Solutions.pdf",
            "size": "666810",
            "version": "July 2016",
            "datePublished": "7/15/2024 4:19:17 AM"
        }
    ],
    "localeDropdown": [
        {
            "cultureCode": "en-us",
            "name": "English"
        }
    ],
    "detailsSection": "Microsoft partner, Vizion Solutions, not only helps its clients visualize Business Intelligence (BI) data in an interactive way, but also positively impacts their business processes, strategy, and bottom line thanks to the intuitive data analytics and visualization capabilities of Power BI.",
    "detailsSection_kbArticles": {
        "link": "http://support.microsoft.com/kb/",
        "name": ""
    },
    "detailsSection_securityBulletins": {
        "link": "http://technet.microsoft.com/en-us/security/Bulletin/",
        "name": ""
    },
    "detailsSection_file_version": "July 2016",
    "detailsSection_file_name": [
        "PowerBI CSP CaseStudy_Vizion Solutions.pdf"
    ],
    "detailsSection_file_size": [
        "651.2 KB"
    ],
    "detailsSection_file_date": "7/15/2024",
    "systemRequirementsSection": "none",
    "systemRequirementsSection_supportedOS": [
        "Windows 10",
        "Windows 7",
        "Windows 8"
    ],
    "installInstructionSection": "Download the file.",
    "relatedResourcesSection": [],
    "locale": "en-us",
    "detailsId": "53156",
    "downloadPreload": true
}