{
    "error": "",
    "downloadTitle": "Cloud PBX with PSTN Calling Technical Readiness Presentation",
    "downloadDescription": "PPT: Cloud PBX with PSTN Calling Technical Readiness ",
    "downloadFile": [
        {
            "isPrimary": "False",
            "name": "Cloud_PBX_PSTN_Calling_Technical Readiness.pptx",
            "url": "https://download.microsoft.com/download/5/a/4/5a49ee3d-cad5-40be-9190-e79ff96a57b0/Cloud_PBX_PSTN_Calling_Technical Readiness.pptx",
            "size": "1728671",
            "version": "Dec 2016",
            "datePublished": "7/15/2024 4:36:48 AM"
        }
    ],
    "localeDropdown": [
        {
            "cultureCode": "en-us",
            "name": "English"
        }
    ],
    "detailsSection": "Cloud PBX with PSTN Calling Technical Readiness Presentation\r\n",
    "detailsSection_kbArticles": {
        "link": "http://support.microsoft.com/kb/",
        "name": ""
    },
    "detailsSection_securityBulletins": {
        "link": "http://technet.microsoft.com/en-us/security/Bulletin/",
        "name": ""
    },
    "detailsSection_file_version": "Dec 2016",
    "detailsSection_file_name": [
        "Cloud_PBX_PSTN_Calling_Technical Readiness.pptx"
    ],
    "detailsSection_file_size": [
        "1.6 MB"
    ],
    "detailsSection_file_date": "7/15/2024",
    "systemRequirementsSection": "Any",
    "systemRequirementsSection_supportedOS": [
        "Windows 10"
    ],
    "installInstructionSection": "Download PPT",
    "relatedResourcesSection": [],
    "locale": "en-us",
    "detailsId": "54422",
    "downloadPreload": true
}