{
    "error": "",
    "downloadTitle": "Office 2010 Customer Success Stories Around the World",
    "downloadDescription": "Office 2010 Impacts the World's Productivity",
    "downloadFile": [
        {
            "isPrimary": "False",
            "name": "Office-2010-Customer-Success-Stories-Around-the-World-Work-with-Powerful-Solutions.pdf",
            "url": "https://download.microsoft.com/download/e/3/c/e3c16625-8238-497f-bd59-9475fb163568/Office-2010-Customer-Success-Stories-Around-the-World-Work-with-Powerful-Solutions.pdf",
            "size": "860713",
            "version": "Final",
            "datePublished": "7/15/2024 3:27:24 AM"
        },
        {
            "isPrimary": "False",
            "name": "Office-2010-Customer-Success-Stories-Around-the-World-Work-Better-Together.pdf",
            "url": "https://download.microsoft.com/download/e/3/c/e3c16625-8238-497f-bd59-9475fb163568/Office-2010-Customer-Success-Stories-Around-the-World-Work-Better-Together.pdf",
            "size": "852899",
            "version": "Final",
            "datePublished": "7/15/2024 3:27:24 AM"
        },
        {
            "isPrimary": "False",
            "name": "Office-2010-Customer-Success-Stories-Around-the-World-Bring-Your-Ideas-to-Life.pdf",
            "url": "https://download.microsoft.com/download/e/3/c/e3c16625-8238-497f-bd59-9475fb163568/Office-2010-Customer-Success-Stories-Around-the-World-Bring-Your-Ideas-to-Life.pdf",
            "size": "856389",
            "version": "Final",
            "datePublished": "7/15/2024 3:27:24 AM"
        },
        {
            "isPrimary": "True",
            "name": "Office-2010-Customer-Success-Stories-Around-the-World-Map.pdf",
            "url": "https://download.microsoft.com/download/e/3/c/e3c16625-8238-497f-bd59-9475fb163568/Office-2010-Customer-Success-Stories-Around-the-World-Map.pdf",
            "size": "1578442",
            "version": "Final",
            "datePublished": "7/15/2024 3:27:24 AM"
        },
        {
            "isPrimary": "False",
            "name": "Office-2010-Customer-Success-Stories-Around-the-World-Work-From-Anywhere.pdf",
            "url": "https://download.microsoft.com/download/e/3/c/e3c16625-8238-497f-bd59-9475fb163568/Office-2010-Customer-Success-Stories-Around-the-World-Work-From-Anywhere.pdf",
            "size": "858364",
            "version": "Final",
            "datePublished": "7/15/2024 3:27:24 AM"
        }
    ],
    "localeDropdown": [
        {
            "cultureCode": "fa-ir",
            "name": "Persian"
        },
        {
            "cultureCode": "pa-in",
            "name": "Punjabi"
        },
        {
            "cultureCode": "kn-in",
            "name": "Kannada"
        },
        {
            "cultureCode": "mr-in",
            "name": "Marathi"
        },
        {
            "cultureCode": "fi-fi",
            "name": "Finnish"
        },
        {
            "cultureCode": "az-latn-az",
            "name": "Azeri (Latin)"
        },
        {
            "cultureCode": "it-it",
            "name": "Italian"
        },
        {
            "cultureCode": "nso-za",
            "name": "Sesotho sa Leboa"
        },
        {
            "cultureCode": "xv-es",
            "name": "Valencian - Spain"
        },
        {
            "cultureCode": "is-is",
            "name": "Icelandic"
        },
        {
            "cultureCode": "tk-tm",
            "name": "Turkmen (Latin) - Turkmenistan"
        },
        {
            "cultureCode": "xc-cher-us",
            "name": "Cherokee - Cherokee Script"
        },
        {
            "cultureCode": "quz-pe",
            "name": "Quechua (Peru)"
        },
        {
            "cultureCode": "ru-ru",
            "name": "Russian"
        },
        {
            "cultureCode": "fil-ph",
            "name": "Filipino"
        },
        {
            "cultureCode": "ro-ro",
            "name": "Romanian"
        },
        {
            "cultureCode": "lo-la",
            "name": "Lao"
        },
        {
            "cultureCode": "he-il",
            "name": "Hebrew"
        },
        {
            "cultureCode": "prs-af",
            "name": "Dari"
        },
        {
            "cultureCode": "ca-es",
            "name": "Catalan"
        },
        {
            "cultureCode": "rw-rw",
            "name": "Kinyarwanda"
        },
        {
            "cultureCode": "uk-ua",
            "name": "Ukrainian"
        },
        {
            "cultureCode": "zh-tw",
            "name": "Chinese (Traditional)"
        },
        {
            "cultureCode": "ko-kr",
            "name": "Korean"
        },
        {
            "cultureCode": "be-by",
            "name": "Belarusian"
        },
        {
            "cultureCode": "ur-in",
            "name": "Urdu"
        },
        {
            "cultureCode": "en-us",
            "name": "English"
        },
        {
            "cultureCode": "mt-mt",
            "name": "Maltese"
        },
        {
            "cultureCode": "tn-bw",
            "name": "Setswana (Botswana)"
        },
        {
            "cultureCode": "ur-pk",
            "name": "Urdu - Pakistan"
        },
        {
            "cultureCode": "rm-ch",
            "name": "Romansh"
        },
        {
            "cultureCode": "gl-es",
            "name": "Galician"
        },
        {
            "cultureCode": "zu-za",
            "name": "isiZulu"
        },
        {
            "cultureCode": "tr-tr",
            "name": "Turkish"
        },
        {
            "cultureCode": "kok-in",
            "name": "Konkani"
        },
        {
            "cultureCode": "eu-es",
            "name": "Basque"
        },
        {
            "cultureCode": "bs-cyrl-ba",
            "name": "Bosnian (Cyrillic)"
        },
        {
            "cultureCode": "zh-cn",
            "name": "Chinese (Simplified)"
        },
        {
            "cultureCode": "mi-nz",
            "name": "M\u0101ori"
        },
        {
            "cultureCode": "sk-sk",
            "name": "Slovak"
        },
        {
            "cultureCode": "sr-latn-rs",
            "name": "Serbian (Latin)"
        },
        {
            "cultureCode": "el-gr",
            "name": "Greek"
        },
        {
            "cultureCode": "ar-sa",
            "name": "Arabic"
        },
        {
            "cultureCode": "ig-ng",
            "name": "Igbo"
        },
        {
            "cultureCode": "nn-no",
            "name": "Norwegian (Nynorsk)"
        },
        {
            "cultureCode": "sr-cyrl-rs",
            "name": "Serbian (Cyrillic)"
        },
        {
            "cultureCode": "pl-pl",
            "name": "Polish"
        },
        {
            "cultureCode": "sl-si",
            "name": "Slovenian"
        },
        {
            "cultureCode": "ta-in",
            "name": "Tamil"
        },
        {
            "cultureCode": "ti-et",
            "name": "Tigrinya - Ethiopia"
        },
        {
            "cultureCode": "sq-al",
            "name": "Albanian"
        },
        {
            "cultureCode": "nb-no",
            "name": "Norwegian (Bokm\u00e5l)"
        },
        {
            "cultureCode": "lb-lu",
            "name": "Luxembourgish"
        },
        {
            "cultureCode": "ha-latn-ng",
            "name": "Hausa"
        },
        {
            "cultureCode": "qut-gt",
            "name": "Kiche - Guatemala"
        },
        {
            "cultureCode": "guc-co",
            "name": "Wayuu - Columbia"
        },
        {
            "cultureCode": "hi-in",
            "name": "Hindi"
        },
        {
            "cultureCode": "xh-za",
            "name": "isiXhosa"
        },
        {
            "cultureCode": "ku-arab-iq",
            "name": "Central Kurdish - Iraq"
        },
        {
            "cultureCode": "cs-cz",
            "name": "Czech"
        },
        {
            "cultureCode": "ky-kg",
            "name": "Kyrgyz"
        },
        {
            "cultureCode": "hy-am",
            "name": "Armenian"
        },
        {
            "cultureCode": "am-et",
            "name": "Amharic"
        },
        {
            "cultureCode": "ka-ge",
            "name": "Georgian"
        },
        {
            "cultureCode": "bg-bg",
            "name": "Bulgarian"
        },
        {
            "cultureCode": "bs-ba",
            "name": "Bosnian (Latin)"
        },
        {
            "cultureCode": "wo-sn",
            "name": "Wolof"
        },
        {
            "cultureCode": "gu-in",
            "name": "Gujarati"
        },
        {
            "cultureCode": "te-in",
            "name": "Telugu"
        },
        {
            "cultureCode": "lv-lv",
            "name": "Latvian"
        },
        {
            "cultureCode": "lt-lt",
            "name": "Lithuanian"
        },
        {
            "cultureCode": "th-th",
            "name": "Thai"
        },
        {
            "cultureCode": "cy-gb",
            "name": "Welsh"
        },
        {
            "cultureCode": "pt-br",
            "name": "Portuguese (Brazil)"
        },
        {
            "cultureCode": "ti-er",
            "name": "Tigrinya - Eritrea"
        },
        {
            "cultureCode": "nl-nl",
            "name": "Dutch"
        },
        {
            "cultureCode": "fr-fr",
            "name": "French"
        },
        {
            "cultureCode": "km-kh",
            "name": "Khmer"
        },
        {
            "cultureCode": "uz-latn-uz",
            "name": "Uzbek (Latin)"
        },
        {
            "cultureCode": "ms-bn",
            "name": "Malay (Brunei Darussalam)"
        },
        {
            "cultureCode": "ne-np",
            "name": "Nepali"
        },
        {
            "cultureCode": "sd-arab-pk",
            "name": "Sindhi - Islamic Republic of Pakistan"
        },
        {
            "cultureCode": "de-de",
            "name": "German"
        },
        {
            "cultureCode": "sv-se",
            "name": "Swedish"
        },
        {
            "cultureCode": "et-ee",
            "name": "Estonian"
        },
        {
            "cultureCode": "mn-cyrl-mn",
            "name": "Mongolian (Cyrillic) - Mongolia"
        },
        {
            "cultureCode": "as-in",
            "name": "Assamese"
        },
        {
            "cultureCode": "id-id",
            "name": "Indonesian"
        },
        {
            "cultureCode": "vi-vn",
            "name": "Vietnamese"
        },
        {
            "cultureCode": "af-za",
            "name": "Afrikaans"
        },
        {
            "cultureCode": "kk-kz",
            "name": "Kazakh"
        },
        {
            "cultureCode": "haw-us",
            "name": "Hawaiian - United States"
        },
        {
            "cultureCode": "pt-pt",
            "name": "Portuguese (Portugal)"
        },
        {
            "cultureCode": "bn-in",
            "name": "Bengali (India)"
        },
        {
            "cultureCode": "tn-za",
            "name": "Setswana (South Africa)"
        },
        {
            "cultureCode": "da-dk",
            "name": "Danish"
        },
        {
            "cultureCode": "gd-gb",
            "name": "Scottish Gaelic - United Kingdom"
        },
        {
            "cultureCode": "es-es",
            "name": "Spanish"
        },
        {
            "cultureCode": "br-fr",
            "name": "Breton - France"
        },
        {
            "cultureCode": "tt-ru",
            "name": "Tatar"
        },
        {
            "cultureCode": "yo-ng",
            "name": "Yoruba"
        },
        {
            "cultureCode": "si-lk",
            "name": "Sinhala"
        },
        {
            "cultureCode": "zh-hk",
            "name": "Chinese (Hong Kong SAR)"
        },
        {
            "cultureCode": "sw-ke",
            "name": "Kiswahili"
        },
        {
            "cultureCode": "iu-latn-ca",
            "name": "Inuktitut (Latin)"
        },
        {
            "cultureCode": "ml-in",
            "name": "Malayalam"
        },
        {
            "cultureCode": "ja-zz",
            "name": "Japanese (NEC)"
        },
        {
            "cultureCode": "ga-ie",
            "name": "Irish - Ireland"
        },
        {
            "cultureCode": "hu-hu",
            "name": "Hungarian"
        },
        {
            "cultureCode": "ps-af",
            "name": "Pashto"
        },
        {
            "cultureCode": "ms-my",
            "name": "Malay (Malaysia)"
        },
        {
            "cultureCode": "hr-hr",
            "name": "Croatian"
        },
        {
            "cultureCode": "ja-jp",
            "name": "Japanese"
        },
        {
            "cultureCode": "mk-mk",
            "name": "Macedonian (FYROM)"
        },
        {
            "cultureCode": "or-in",
            "name": "Oriya"
        },
        {
            "cultureCode": "bn-bd",
            "name": "Bangla (Bangledsh) - Bangladesh"
        },
        {
            "cultureCode": "sr-cyrl-ba",
            "name": "Serbian (Cyrillic) - Bosnia and Herzegovina"
        }
    ],
    "detailsSection": "Our customers are standing up for Microsoft Office 2010. Around the world, Microsoft Office 2010 empowers businesses to do more with less, enabling people to do their best work wherever they are, whether on a PC, phone or web browser. It gives people the tools to present powerful ideas in visual and meaningful ways, to share ideas and edit content quickly and easily without needing to be in the same place. Microsoft Office 2010 is compatible with thousands of applications, which means maximum use of existing investments for both customers and partners. \r\n\r\nUse this interactive world map to find customers just like yourself. No matter if you are a small, mid-sized or large company; across all manner of locations and industries, businesses are voting for Microsoft Office 2010. For more information, visit office.microsoft.com.\r\n",
    "detailsSection_kbArticles": {
        "link": "http://support.microsoft.com/kb/",
        "name": ""
    },
    "detailsSection_securityBulletins": {
        "link": "http://technet.microsoft.com/en-us/security/Bulletin/",
        "name": ""
    },
    "detailsSection_file_version": "Final",
    "detailsSection_file_name": [
        "Office-2010-Customer-Success-Stories-Around-the-World-Work-with-Powerful-Solutions.pdf",
        "Office-2010-Customer-Success-Stories-Around-the-World-Work-Better-Together.pdf",
        "Office-2010-Customer-Success-Stories-Around-the-World-Bring-Your-Ideas-to-Life.pdf",
        "Office-2010-Customer-Success-Stories-Around-the-World-Map.pdf",
        "Office-2010-Customer-Success-Stories-Around-the-World-Work-From-Anywhere.pdf"
    ],
    "detailsSection_file_size": [
        "840.5 KB",
        "832.9 KB",
        "836.3 KB",
        "1.5 MB",
        "838.2 KB"
    ],
    "detailsSection_file_date": "7/15/2024",
    "systemRequirementsSection": "To use the interactive features of this tool, you must have Adobe Reader installed on your computer.",
    "systemRequirementsSection_supportedOS": [
        "Apple Mac OS X",
        "Macintosh",
        "Windows 7",
        "Windows 7 Enterprise",
        "Windows 7 Enterprise N",
        "Windows 7 Home Basic",
        "Windows 7 Home Basic 64-bit",
        "Windows 7 Home Premium",
        "Windows 7 Home Premium 64-bit",
        "Windows 7 Home Premium E 64-bit",
        "Windows 7 Home Premium N",
        "Windows 7 Home Premium N 64-bit",
        "Windows 7 Professional",
        "Windows 7 Professional 64-bit",
        "Windows 7 Professional E 64-bit",
        "Windows 7 Professional K 64-bit",
        "Windows 7 Professional KN 64-bit",
        "Windows 7 Professional N",
        "Windows 7 Professional N 64-bit",
        "Windows 7 Service Pack 1",
        "Windows 7 Starter",
        "Windows 7 Starter 64-bit",
        "Windows 7 Starter N",
        "Windows 7 Ultimate",
        "Windows 7 Ultimate 64-bit",
        "Windows 7 Ultimate E 64-bit",
        "Windows 7 Ultimate K 64-bit",
        "Windows 7 Ultimate KN 64-bit",
        "Windows 7 Ultimate N",
        "Windows 7 Ultimate N 64-bit",
        "Windows Phone 7",
        "Windows Vista",
        "Windows Vista 64-bit Editions Service Pack 1",
        "Windows Vista Business",
        "Windows Vista Business 64-bit edition",
        "Windows Vista Business N",
        "Windows Vista Enterprise",
        "Windows Vista Enterprise 64-bit edition",
        "Windows Vista Home Basic",
        "Windows Vista Home Basic 64-bit edition",
        "Windows Vista Home Basic N",
        "Windows Vista Home Premium",
        "Windows Vista Home Premium 64-bit edition",
        "Windows Vista Service Pack 1",
        "Windows Vista Service Pack 2",
        "Windows Vista Starter",
        "Windows Vista Starter N",
        "Windows Vista Ultimate",
        "Windows Vista Ultimate 64-bit edition",
        "Windows XP"
    ],
    "installInstructionSection": "To use the interactive features of this tool, you must have Adobe Reader installed on your computer. Click the Download button to open the file or save it to your computer.",
    "relatedResourcesSection": [],
    "locale": "en-us",
    "detailsId": "26493",
    "downloadPreload": true
}