{
    "error": "",
    "downloadTitle": "Cumulative Update 17 for Microsoft Dynamics NAV 2013 R2",
    "downloadDescription": "Over the last few years we've shipped a series of new releases that have transformed Microsoft Dynamics NAV and your market opportunity. The goal is to make it even easier to use and adding capabilities design to support SMB business ambitions.",
    "downloadFile": [
        {
            "isPrimary": "False",
            "name": "March Update Rollup for Microsoft Dynamics NAV 2013 R2 AU.zip",
            "url": "https://download.microsoft.com/download/e/d/e/ede5a926-ed6e-46f1-b5aa-fb94e6bc55e0/March Update Rollup for Microsoft Dynamics NAV 2013 R2 AU.zip",
            "size": "771030616",
            "version": "7.1.40076",
            "datePublished": "1/15/2024 3:05:40 AM"
        },
        {
            "isPrimary": "False",
            "name": "March Update Rollup for Microsoft Dynamics NAV 2013 R2 ES.zip",
            "url": "https://download.microsoft.com/download/e/d/e/ede5a926-ed6e-46f1-b5aa-fb94e6bc55e0/March Update Rollup for Microsoft Dynamics NAV 2013 R2 ES.zip",
            "size": "775381302",
            "version": "7.1.40076",
            "datePublished": "1/15/2024 3:05:40 AM"
        },
        {
            "isPrimary": "False",
            "name": "March Update Rollup for Microsoft Dynamics NAV 2013 R2 DK.zip",
            "url": "https://download.microsoft.com/download/e/d/e/ede5a926-ed6e-46f1-b5aa-fb94e6bc55e0/March Update Rollup for Microsoft Dynamics NAV 2013 R2 DK.zip",
            "size": "769987696",
            "version": "7.1.40076",
            "datePublished": "1/15/2024 3:05:40 AM"
        },
        {
            "isPrimary": "False",
            "name": "March Update Rollup for Microsoft Dynamics NAV 2013 R2 NO.zip",
            "url": "https://download.microsoft.com/download/e/d/e/ede5a926-ed6e-46f1-b5aa-fb94e6bc55e0/March Update Rollup for Microsoft Dynamics NAV 2013 R2 NO.zip",
            "size": "769853162",
            "version": "7.1.40076",
            "datePublished": "1/15/2024 3:05:40 AM"
        },
        {
            "isPrimary": "False",
            "name": "March Update Rollup for Microsoft Dynamics NAV 2013 R2 W1.zip",
            "url": "https://download.microsoft.com/download/e/d/e/ede5a926-ed6e-46f1-b5aa-fb94e6bc55e0/March Update Rollup for Microsoft Dynamics NAV 2013 R2 W1.zip",
            "size": "744186496",
            "version": "7.1.40076",
            "datePublished": "1/15/2024 3:05:40 AM"
        },
        {
            "isPrimary": "False",
            "name": "March Update Rollup for Microsoft Dynamics NAV 2013 R2 DE.zip",
            "url": "https://download.microsoft.com/download/e/d/e/ede5a926-ed6e-46f1-b5aa-fb94e6bc55e0/March Update Rollup for Microsoft Dynamics NAV 2013 R2 DE.zip",
            "size": "771968204",
            "version": "7.1.40076",
            "datePublished": "1/15/2024 3:05:40 AM"
        },
        {
            "isPrimary": "False",
            "name": "March Update Rollup for Microsoft Dynamics NAV 2013 R2 FI.zip",
            "url": "https://download.microsoft.com/download/e/d/e/ede5a926-ed6e-46f1-b5aa-fb94e6bc55e0/March Update Rollup for Microsoft Dynamics NAV 2013 R2 FI.zip",
            "size": "767011021",
            "version": "7.1.40076",
            "datePublished": "1/15/2024 3:05:40 AM"
        },
        {
            "isPrimary": "False",
            "name": "March Update Rollup for Microsoft Dynamics NAV 2013 R2 BE.zip",
            "url": "https://download.microsoft.com/download/e/d/e/ede5a926-ed6e-46f1-b5aa-fb94e6bc55e0/March Update Rollup for Microsoft Dynamics NAV 2013 R2 BE.zip",
            "size": "784727863",
            "version": "7.1.40076",
            "datePublished": "1/15/2024 3:05:40 AM"
        },
        {
            "isPrimary": "False",
            "name": "March Update Rollup for Microsoft Dynamics NAV 2013 R2 IS.zip",
            "url": "https://download.microsoft.com/download/e/d/e/ede5a926-ed6e-46f1-b5aa-fb94e6bc55e0/March Update Rollup for Microsoft Dynamics NAV 2013 R2 IS.zip",
            "size": "766063992",
            "version": "7.1.40076",
            "datePublished": "1/15/2024 3:05:40 AM"
        },
        {
            "isPrimary": "False",
            "name": "March Update Rollup for Microsoft Dynamics NAV 2013 R2 CH.zip",
            "url": "https://download.microsoft.com/download/e/d/e/ede5a926-ed6e-46f1-b5aa-fb94e6bc55e0/March Update Rollup for Microsoft Dynamics NAV 2013 R2 CH.zip",
            "size": "818866826",
            "version": "7.1.40076",
            "datePublished": "1/15/2024 3:05:40 AM"
        },
        {
            "isPrimary": "False",
            "name": "March Update Rollup for Microsoft Dynamics NAV 2013 R2 FR.zip",
            "url": "https://download.microsoft.com/download/e/d/e/ede5a926-ed6e-46f1-b5aa-fb94e6bc55e0/March Update Rollup for Microsoft Dynamics NAV 2013 R2 FR.zip",
            "size": "769983842",
            "version": "7.1.40076",
            "datePublished": "1/15/2024 3:05:40 AM"
        },
        {
            "isPrimary": "False",
            "name": "March Update Rollup for Microsoft Dynamics NAV 2013 R2 AT.zip",
            "url": "https://download.microsoft.com/download/e/d/e/ede5a926-ed6e-46f1-b5aa-fb94e6bc55e0/March Update Rollup for Microsoft Dynamics NAV 2013 R2 AT.zip",
            "size": "771516802",
            "version": "7.1.40076",
            "datePublished": "1/15/2024 3:05:40 AM"
        },
        {
            "isPrimary": "False",
            "name": "March Update Rollup for Microsoft Dynamics NAV 2013 R2 IT.zip",
            "url": "https://download.microsoft.com/download/e/d/e/ede5a926-ed6e-46f1-b5aa-fb94e6bc55e0/March Update Rollup for Microsoft Dynamics NAV 2013 R2 IT.zip",
            "size": "774015317",
            "version": "7.1.40076",
            "datePublished": "1/15/2024 3:05:40 AM"
        },
        {
            "isPrimary": "False",
            "name": "March Update Rollup for Microsoft Dynamics NAV 2013 R2 NL.zip",
            "url": "https://download.microsoft.com/download/e/d/e/ede5a926-ed6e-46f1-b5aa-fb94e6bc55e0/March Update Rollup for Microsoft Dynamics NAV 2013 R2 NL.zip",
            "size": "769430285",
            "version": "7.1.40076",
            "datePublished": "1/15/2024 3:05:40 AM"
        },
        {
            "isPrimary": "False",
            "name": "March Update Rollup for Microsoft Dynamics NAV 2013 R2 CZ.zip",
            "url": "https://download.microsoft.com/download/e/d/e/ede5a926-ed6e-46f1-b5aa-fb94e6bc55e0/March Update Rollup for Microsoft Dynamics NAV 2013 R2 CZ.zip",
            "size": "781810337",
            "version": "7.1.40076",
            "datePublished": "1/15/2024 3:05:40 AM"
        },
        {
            "isPrimary": "False",
            "name": "March Update Rollup for Microsoft Dynamics NAV 2013 R2 NA.zip",
            "url": "https://download.microsoft.com/download/e/d/e/ede5a926-ed6e-46f1-b5aa-fb94e6bc55e0/March Update Rollup for Microsoft Dynamics NAV 2013 R2 NA.zip",
            "size": "826205315",
            "version": "7.1.40076",
            "datePublished": "1/15/2024 3:05:40 AM"
        },
        {
            "isPrimary": "False",
            "name": "March Update Rollup for Microsoft Dynamics NAV 2013 R2 RU.zip",
            "url": "https://download.microsoft.com/download/e/d/e/ede5a926-ed6e-46f1-b5aa-fb94e6bc55e0/March Update Rollup for Microsoft Dynamics NAV 2013 R2 RU.zip",
            "size": "807521578",
            "version": "7.1.40076",
            "datePublished": "1/15/2024 3:05:40 AM"
        },
        {
            "isPrimary": "False",
            "name": "March Update Rollup for Microsoft Dynamics NAV 2013 R2 GB.zip",
            "url": "https://download.microsoft.com/download/e/d/e/ede5a926-ed6e-46f1-b5aa-fb94e6bc55e0/March Update Rollup for Microsoft Dynamics NAV 2013 R2 GB.zip",
            "size": "766273355",
            "version": "7.1.40076",
            "datePublished": "1/15/2024 3:05:40 AM"
        },
        {
            "isPrimary": "False",
            "name": "March Update Rollup for Microsoft Dynamics NAV 2013 R2 SE.zip",
            "url": "https://download.microsoft.com/download/e/d/e/ede5a926-ed6e-46f1-b5aa-fb94e6bc55e0/March Update Rollup for Microsoft Dynamics NAV 2013 R2 SE.zip",
            "size": "767846459",
            "version": "7.1.40076",
            "datePublished": "1/15/2024 3:05:40 AM"
        },
        {
            "isPrimary": "False",
            "name": "March Update Rollup for Microsoft Dynamics NAV 2013 R2 NZ.zip",
            "url": "https://download.microsoft.com/download/e/d/e/ede5a926-ed6e-46f1-b5aa-fb94e6bc55e0/March Update Rollup for Microsoft Dynamics NAV 2013 R2 NZ.zip",
            "size": "770526823",
            "version": "7.1.40076",
            "datePublished": "1/15/2024 3:05:40 AM"
        }
    ],
    "localeDropdown": [
        {
            "cultureCode": "en-us",
            "name": "English"
        }
    ],
    "detailsSection": "To learn more about what is included in this cumulative update please visit this kb article:\r\nhttps://support.microsoft.com/en-us/help/3039826 \r\n\r\nTo learn more about other cumulative updates already released for Microsoft Dynamics NAV 2013 please see this kb article:\r\nhttps://support.microsoft.com/en-us/help/2842257\r\n",
    "detailsSection_kbArticles": {
        "link": "http://support.microsoft.com/kb/",
        "name": ""
    },
    "detailsSection_securityBulletins": {
        "link": "http://technet.microsoft.com/en-us/security/Bulletin/",
        "name": ""
    },
    "detailsSection_file_version": "7.1.40076",
    "detailsSection_file_name": [
        "March Update Rollup for Microsoft Dynamics NAV 2013 R2 AU.zip",
        "March Update Rollup for Microsoft Dynamics NAV 2013 R2 ES.zip",
        "March Update Rollup for Microsoft Dynamics NAV 2013 R2 DK.zip",
        "March Update Rollup for Microsoft Dynamics NAV 2013 R2 NO.zip",
        "March Update Rollup for Microsoft Dynamics NAV 2013 R2 W1.zip",
        "March Update Rollup for Microsoft Dynamics NAV 2013 R2 DE.zip",
        "March Update Rollup for Microsoft Dynamics NAV 2013 R2 FI.zip",
        "March Update Rollup for Microsoft Dynamics NAV 2013 R2 BE.zip",
        "March Update Rollup for Microsoft Dynamics NAV 2013 R2 IS.zip",
        "March Update Rollup for Microsoft Dynamics NAV 2013 R2 CH.zip",
        "March Update Rollup for Microsoft Dynamics NAV 2013 R2 FR.zip",
        "March Update Rollup for Microsoft Dynamics NAV 2013 R2 AT.zip",
        "March Update Rollup for Microsoft Dynamics NAV 2013 R2 IT.zip",
        "March Update Rollup for Microsoft Dynamics NAV 2013 R2 NL.zip",
        "March Update Rollup for Microsoft Dynamics NAV 2013 R2 CZ.zip",
        "March Update Rollup for Microsoft Dynamics NAV 2013 R2 NA.zip",
        "March Update Rollup for Microsoft Dynamics NAV 2013 R2 RU.zip",
        "March Update Rollup for Microsoft Dynamics NAV 2013 R2 GB.zip",
        "March Update Rollup for Microsoft Dynamics NAV 2013 R2 SE.zip",
        "March Update Rollup for Microsoft Dynamics NAV 2013 R2 NZ.zip"
    ],
    "detailsSection_file_size": [
        "735.3 MB",
        "739.5 MB",
        "734.3 MB",
        "734.2 MB",
        "709.7 MB",
        "736.2 MB",
        "731.5 MB",
        "748.4 MB",
        "730.6 MB",
        "780.9 MB",
        "734.3 MB",
        "735.8 MB",
        "738.2 MB",
        "733.8 MB",
        "745.6 MB",
        "787.9 MB",
        "770.1 MB",
        "730.8 MB",
        "732.3 MB",
        "734.8 MB"
    ],
    "detailsSection_file_date": "1/15/2024",
    "systemRequirementsSection": "Requirements can be found at:\r\nhttps://docs.microsoft.com/en-us/dynamics-nav/system-requirements-for-microsoft-dynamics-nav\r\n",
    "systemRequirementsSection_supportedOS": [
        "Windows 10",
        "Windows 7",
        "Windows 8"
    ],
    "installInstructionSection": "How to install this Cumulative Update\r\nhttps://support.microsoft.com/en-us/help/2834770\r\n",
    "relatedResourcesSection": [],
    "locale": "en-us",
    "detailsId": "57945",
    "downloadPreload": true
}